{
  "movies": [
    {
      "title": "MIB: Homens de Preto III (2012)",
      "urlPhoto": "https://m.media-amazon.com/images/M/MV5BMTU2NTYxODcwMF5BMl5BanBnXkFtZTcwNDk1NDY0Nw@@._V1_UX182_CR0,0,182,268_AL_.jpg",
      "dateRelease": "2021-02-01T03:00:00.000Z",
      "description": "Agent J travels in time to M.I.B.'s early days in 1969 to stop an alien from assassinating his friend Agent K and changing history.",
      "urlIMDb": "https://www.imdb.com/title/tt1409024/?ref_=hm_tpks_tt_9_pd_tp1_cp",
      "genre": "Comedy",
      "id": 2
    },
    {
      "title": "Godzilla vs. Kong (2021)",
      "urlPhoto": "https://m.media-amazon.com/images/M/MV5BZmYzMzU4NjctNDI0Mi00MGExLWI3ZDQtYzQzYThmYzc2ZmNjXkEyXkFqcGdeQXVyMTEyMjM2NDc2._V1_UX182_CR0,0,182,268_AL_.jpg",
      "dateRelease": "2021-02-01T03:00:00.000Z",
      "description": "The epic next chapter in the cinematic Monsterverse pits two of the greatest icons in motion picture history against one another - the fearsome Godzilla and the mighty Kong - with humanity caught in the balance.",
      "urlIMDb": "https://www.imdb.com/title/tt5034838/?ref_=vp_vi_tt",
      "genre": "Science fiction",
      "id": 3
    }
  ]
}